exportsgalore/__init__.py
exportsgalore/comtrade.py
exportsgalore/imf.py
api_export_data-0.0.1.dist-info/LICENSE
api_export_data-0.0.1.dist-info/METADATA
api_export_data-0.0.1.dist-info/WHEEL
api_export_data-0.0.1.dist-info/top_level.txt
api_export_data-0.0.1.dist-info/RECORD
