Metadata-Version: 2.1
Name: api_export_data
Version: 0.0.1
Summary: A package that facilitates API calls to UN Comtrade and the International Monetary Fund to gather macroeconomic export data
Author-email: Paul Dilly <paul.dilly@duke.edu>
Project-URL: Homepage, https://github.com/pcd15/api_export_data
Classifier: Programming Language :: Python :: 3
Classifier: License :: OSI Approved :: MIT License
Classifier: Operating System :: OS Independent
Requires-Python: >=3.7
License-File: LICENSE
